EasyFileOps/__init__.py
EasyFileOps/file.py
EasyFileOps-0.1.71.dist-info/METADATA
EasyFileOps-0.1.71.dist-info/WHEEL
EasyFileOps-0.1.71.dist-info/top_level.txt
EasyFileOps-0.1.71.dist-info/RECORD
