Metadata-Version: 2.1
Name: EasyFileOps
Version: 0.1.71
Summary: EasyFileOps helps with operating on files in python
Author: RaiderHCPlay
License: MIT
